LICENSE
README.md
setup.cfg
setup.py
NLaser/NLaser.py
NLaser/__init__.py
NLaser.egg-info/PKG-INFO
NLaser.egg-info/SOURCES.txt
NLaser.egg-info/dependency_links.txt
NLaser.egg-info/requires.txt
NLaser.egg-info/top_level.txt