Metadata-Version: 2.1
Name: NLaser
Version: 0.0.1
Summary: It is a Python library for the N-PLS1 regression with L2-regularization.
Home-page: https://github.com/89605502155/N-PLS
Author: Andrey Ferubko and Ivan Krylov
Author-email: ferubko1999@yandex.ru
License: GNU General Public License v3.0
Download-URL: https://github.com/89605502155/N-PLS/archive/main.zip
Platform: UNKNOWN
Classifier: License :: OSI Approved :: GNU General Public License v3 (GPLv3)
Classifier: Operating System :: OS Independent
Classifier: Intended Audience :: End Users/Desktop
Classifier: Intended Audience :: Developers
Classifier: Programming Language :: Python
Classifier: Programming Language :: Python :: 3
Classifier: Programming Language :: Python :: 3.9
Classifier: Programming Language :: Python :: 3.10
Classifier: Programming Language :: Python :: 3.11
Classifier: Programming Language :: Python :: 3.8
Classifier: Programming Language :: Python :: Implementation :: PyPy
Classifier: Programming Language :: Python :: Implementation :: CPython
License-File: LICENSE
